{
    "meta": {
        "縣市別": "南投縣",
        "鄉鎮市區": "竹山鎮",
        "清運路線序號": "M55720005",
        "清運路線名稱": "中山里.桶頭里.瑞竹里.坪頂里.中崎里.回遙里.雲林里路線",
        "清運方式": "沿線清運(不落地)",
        "清運車輛車號": "683UQ(備用車號:976VE)",
        "清運路線距離(公里)": "74.00",
        "每日清運垃圾量(公噸\/日)": "3.64",
        "清運頻率(週)": "3",
        "清運頻率(日)": "1"
    },
    "points": [
        {
            "清運序": "1",
            "清運點名稱描述": "中山里",
            "清運時間": "16:30",
            "一般垃圾": "一、三、五",
            "廚餘回收": "一、三、五",
            "資源回收": "一、三、五"
        },
        {
            "清運序": "2",
            "清運點名稱描述": "桶頭里",
            "清運時間": "16:30",
            "一般垃圾": "一、三、五",
            "廚餘回收": "一、三、五",
            "資源回收": "一、三、五"
        },
        {
            "清運序": "3",
            "清運點名稱描述": "瑞竹里",
            "清運時間": "16:30",
            "一般垃圾": "一、三、五",
            "廚餘回收": "一、三、五",
            "資源回收": "一、三、五"
        },
        {
            "清運序": "4",
            "清運點名稱描述": "坪頂里",
            "清運時間": "16:30",
            "一般垃圾": "一、三、五",
            "廚餘回收": "一、三、五",
            "資源回收": "一、三、五"
        },
        {
            "清運序": "5",
            "清運點名稱描述": "中崎里",
            "清運時間": "16:30",
            "一般垃圾": "一、三、五",
            "廚餘回收": "一、三、五",
            "資源回收": "一、三、五"
        },
        {
            "清運序": "6",
            "清運點名稱描述": "回遙里",
            "清運時間": "16:30",
            "一般垃圾": "一、三、五",
            "廚餘回收": "一、三、五",
            "資源回收": "一、三、五"
        },
        {
            "清運序": "7",
            "清運點名稱描述": "雲林里",
            "清運時間": "16:30",
            "一般垃圾": "一、三、五",
            "廚餘回收": "一、三、五",
            "資源回收": "一、三、五"
        }
    ]
}