{
    "meta": {
        "縣市別": "彰化縣",
        "鄉鎮市區": "二水鄉",
        "清運路線序號": "N53020011",
        "清運路線名稱": "2車一三五路線",
        "清運方式": "沿線清運(不落地)",
        "清運車輛車號": "702VQ(備用車號:)",
        "清運路線距離(公里)": "25.00",
        "每日清運垃圾量(公噸\/日)": "2.80",
        "清運頻率(週)": "3",
        "清運頻率(日)": "1"
    },
    "points": [
        {
            "清運序": "1",
            "清運點名稱描述": "民生路萬通修理廠",
            "清運時間": "17:00",
            "一般垃圾": "一、三、五",
            "廚餘回收": "一、三、五",
            "資源回收": "一、五"
        },
        {
            "清運序": "2",
            "清運點名稱描述": "立典電機",
            "清運時間": "17:03",
            "一般垃圾": "一、三、五",
            "廚餘回收": "一、三、五",
            "資源回收": "一、五"
        },
        {
            "清運序": "3",
            "清運點名稱描述": "南通路稻草人檳榔",
            "清運時間": "17:04",
            "一般垃圾": "一、三、五",
            "廚餘回收": "一、三、五",
            "資源回收": "一、五"
        },
        {
            "清運序": "4",
            "清運點名稱描述": "南通路西邊沿路住戶",
            "清運時間": "17:05",
            "一般垃圾": "一、三、五",
            "廚餘回收": "一、三、五",
            "資源回收": "一、五"
        },
        {
            "清運序": "5",
            "清運點名稱描述": "修玄宮",
            "清運時間": "17:07",
            "一般垃圾": "一、三、五",
            "廚餘回收": "一、三、五",
            "資源回收": "一、五"
        },
        {
            "清運序": "6",
            "清運點名稱描述": "元帝廟",
            "清運時間": "17:10",
            "一般垃圾": "一、三、五",
            "廚餘回收": "一、三、五",
            "資源回收": "一、五"
        },
        {
            "清運序": "7",
            "清運點名稱描述": "清玉都石玉坊",
            "清運時間": "17:11",
            "一般垃圾": "一、三、五",
            "廚餘回收": "一、三、五",
            "資源回收": "一、五"
        },
        {
            "清運序": "8",
            "清運點名稱描述": "南通路2段1號迴轉",
            "清運時間": "17:13",
            "一般垃圾": "一、三、五",
            "廚餘回收": "一、三、五",
            "資源回收": "一、五"
        },
        {
            "清運序": "9",
            "清運點名稱描述": "南通路東邊沿路住戶",
            "清運時間": "17:15",
            "一般垃圾": "一、三、五",
            "廚餘回收": "一、三、五",
            "資源回收": "一、五"
        },
        {
            "清運序": "10",
            "清運點名稱描述": "嘉景草皮農場",
            "清運時間": "17:17",
            "一般垃圾": "一、三、五",
            "廚餘回收": "一、三、五",
            "資源回收": "一、五"
        },
        {
            "清運序": "11",
            "清運點名稱描述": "阿英檳榔攤",
            "清運時間": "17:19",
            "一般垃圾": "一、三、五",
            "廚餘回收": "一、三、五",
            "資源回收": "一、五"
        },
        {
            "清運序": "12",
            "清運點名稱描述": "國蘭新城",
            "清運時間": "17:21",
            "一般垃圾": "一、三、五",
            "廚餘回收": "一、三、五",
            "資源回收": "一、五"
        },
        {
            "清運序": "13",
            "清運點名稱描述": "喬琦工業迴轉",
            "清運時間": "17:23",
            "一般垃圾": "一、三、五",
            "廚餘回收": "一、三、五",
            "資源回收": "一、五"
        },
        {
            "清運序": "14",
            "清運點名稱描述": "羽台",
            "清運時間": "17:26",
            "一般垃圾": "一、三、五",
            "廚餘回收": "一、三、五",
            "資源回收": "一、五"
        },
        {
            "清運序": "15",
            "清運點名稱描述": "中油加油站",
            "清運時間": "17:30",
            "一般垃圾": "一、三、五",
            "廚餘回收": "一、三、五",
            "資源回收": "一、五"
        },
        {
            "清運序": "16",
            "清運點名稱描述": "民生路宏新汽車",
            "清運時間": "17:32",
            "一般垃圾": "一、三、五",
            "廚餘回收": "一、三、五",
            "資源回收": "一、五"
        },
        {
            "清運序": "17",
            "清運點名稱描述": "卓昭文家",
            "清運時間": "17:33",
            "一般垃圾": "一、三、五",
            "廚餘回收": "一、三、五",
            "資源回收": "一、五"
        },
        {
            "清運序": "18",
            "清運點名稱描述": "民生路與文昌路檳榔攤",
            "清運時間": "17:34",
            "一般垃圾": "一、三、五",
            "廚餘回收": "一、三、五",
            "資源回收": "一、五"
        },
        {
            "清運序": "19",
            "清運點名稱描述": "合興村谷昌瀝青",
            "清運時間": "17:38",
            "一般垃圾": "一、三、五",
            "廚餘回收": "一、三、五",
            "資源回收": "一、五"
        },
        {
            "清運序": "20",
            "清運點名稱描述": "沿鼻倡路",
            "清運時間": "17:41",
            "一般垃圾": "一、三、五",
            "廚餘回收": "一、三、五",
            "資源回收": "一、五"
        },
        {
            "清運序": "21",
            "清運點名稱描述": "鄭利行家",
            "清運時間": "17:42",
            "一般垃圾": "一、三、五",
            "廚餘回收": "一、三、五",
            "資源回收": "一、五"
        },
        {
            "清運序": "22",
            "清運點名稱描述": "鼻倡路14號",
            "清運時間": "17:43",
            "一般垃圾": "一、三、五",
            "廚餘回收": "一、三、五",
            "資源回收": "一、五"
        },
        {
            "清運序": "23",
            "清運點名稱描述": "鼻倡路陳有朋家",
            "清運時間": "17:44",
            "一般垃圾": "一、三、五",
            "廚餘回收": "一、三、五",
            "資源回收": "一、五"
        },
        {
            "清運序": "24",
            "清運點名稱描述": "鼻倡路與員集路交叉口",
            "清運時間": "17:45",
            "一般垃圾": "一、三、五",
            "廚餘回收": "一、三、五",
            "資源回收": "一、五"
        },
        {
            "清運序": "25",
            "清運點名稱描述": "源泉村福龍別墅",
            "清運時間": "17:47",
            "一般垃圾": "一、三、五",
            "廚餘回收": "一、三、五",
            "資源回收": "一、五"
        },
        {
            "清運序": "26",
            "清運點名稱描述": "文化村電信機房後巷",
            "清運時間": "17:50",
            "一般垃圾": "一、三、五",
            "廚餘回收": "一、三、五",
            "資源回收": "一、五"
        },
        {
            "清運序": "27",
            "清運點名稱描述": "聖化村基督教堂",
            "清運時間": "17:53",
            "一般垃圾": "一、三、五",
            "廚餘回收": "一、三、五",
            "資源回收": "一、五"
        },
        {
            "清運序": "28",
            "清運點名稱描述": "溪邊巷大時代托兒所",
            "清運時間": "17:54",
            "一般垃圾": "一、三、五",
            "廚餘回收": "一、三、五",
            "資源回收": "一、五"
        },
        {
            "清運序": "29",
            "清運點名稱描述": "橋上右岸邊住家",
            "清運時間": "17:55",
            "一般垃圾": "一、三、五",
            "廚餘回收": "一、三、五",
            "資源回收": "一、五"
        },
        {
            "清運序": "30",
            "清運點名稱描述": "曾劍煌診所",
            "清運時間": "17:56",
            "一般垃圾": "一、三、五",
            "廚餘回收": "一、三、五",
            "資源回收": "一、五"
        },
        {
            "清運序": "31",
            "清運點名稱描述": "農會",
            "清運時間": "17:57",
            "一般垃圾": "一、三、五",
            "廚餘回收": "一、三、五",
            "資源回收": "一、五"
        },
        {
            "清運序": "32",
            "清運點名稱描述": "衛生所",
            "清運時間": "17:59",
            "一般垃圾": "一、三、五",
            "廚餘回收": "一、三、五",
            "資源回收": "一、五"
        },
        {
            "清運序": "33",
            "清運點名稱描述": "大時代補習班",
            "清運時間": "18:00",
            "一般垃圾": "一、三、五",
            "廚餘回收": "一、三、五",
            "資源回收": "一、五"
        },
        {
            "清運序": "34",
            "清運點名稱描述": "過圳路與民生路十字路口",
            "清運時間": "18:02",
            "一般垃圾": "一、三、五",
            "廚餘回收": "一、三、五",
            "資源回收": "一、五"
        },
        {
            "清運序": "35",
            "清運點名稱描述": "陳大森家",
            "清運時間": "18:15",
            "一般垃圾": "一、三、五",
            "廚餘回收": "一、三、五",
            "資源回收": "一、五"
        },
        {
            "清運序": "36",
            "清運點名稱描述": "羅森澤家",
            "清運時間": "18:25",
            "一般垃圾": "一、三、五",
            "廚餘回收": "一、三、五",
            "資源回收": "一、五"
        }
    ]
}