{
    "meta": {
        "縣市別": "臺中市",
        "鄉鎮市區": "大雅區",
        "清運路線序號": "B42820013",
        "清運路線名稱": "日間線路七",
        "清運方式": "沿線清運(不落地)",
        "清運車輛車號": "037VP(備用車號:) 407VP(備用車號:) 005UR(備用車號:)",
        "清運路線距離(公里)": "62.00",
        "每日清運垃圾量(公噸\/日)": "3.83",
        "清運頻率(週)": "5",
        "清運頻率(日)": "1"
    },
    "points": [
        {
            "清運序": "2",
            "清運點名稱描述": "臺中市大雅區神林南路661號",
            "清運時間": "07:20",
            "一般垃圾": "一、二、四、五、六",
            "廚餘回收": "一、二、四、五、六",
            "資源回收": "一、二、四、五、六"
        },
        {
            "清運序": "3",
            "清運點名稱描述": "臺中市大雅區學府路49號",
            "清運時間": "07:25",
            "一般垃圾": "一、二、四、五、六",
            "廚餘回收": "一、二、四、五、六",
            "資源回收": "一、二、四、五、六"
        },
        {
            "清運序": "4",
            "清運點名稱描述": "臺中市大雅區學府路23巷6號",
            "清運時間": "07:28",
            "一般垃圾": "一、二、四、五、六",
            "廚餘回收": "一、二、四、五、六",
            "資源回收": "一、二、四、五、六"
        },
        {
            "清運序": "5",
            "清運點名稱描述": "臺中市大雅區學府路101巷1號",
            "清運時間": "07:32",
            "一般垃圾": "一、二、四、五、六",
            "廚餘回收": "一、二、四、五、六",
            "資源回收": "一、二、四、五、六"
        },
        {
            "清運序": "6",
            "清運點名稱描述": "臺中市大雅區學府路76巷75號",
            "清運時間": "07:35",
            "一般垃圾": "一、二、四、五、六",
            "廚餘回收": "一、二、四、五、六",
            "資源回收": "一、二、四、五、六"
        },
        {
            "清運序": "7",
            "清運點名稱描述": "臺中市大雅區雅環路一段106巷18號",
            "清運時間": "07:40",
            "一般垃圾": "一、二、四、五、六",
            "廚餘回收": "一、二、四、五、六",
            "資源回收": "一、二、四、五、六"
        },
        {
            "清運序": "8",
            "清運點名稱描述": "臺中市大雅區義和路6-6號",
            "清運時間": "07:55",
            "一般垃圾": "一、二、四、五、六",
            "廚餘回收": "一、二、四、五、六",
            "資源回收": "一、二、四、五、六"
        },
        {
            "清運序": "9",
            "清運點名稱描述": "臺中市大雅區仁和路86號",
            "清運時間": "08:00",
            "一般垃圾": "一、二、四、五、六",
            "廚餘回收": "一、二、四、五、六",
            "資源回收": "一、二、四、五、六"
        },
        {
            "清運序": "10",
            "清運點名稱描述": "臺中市大雅區田心一街21號",
            "清運時間": "08:03",
            "一般垃圾": "一、二、四、五、六",
            "廚餘回收": "一、二、四、五、六",
            "資源回收": "一、二、四、五、六"
        },
        {
            "清運序": "11",
            "清運點名稱描述": "臺中市大雅區神林南路313巷17弄1號",
            "清運時間": "08:08",
            "一般垃圾": "一、二、四、五、六",
            "廚餘回收": "一、二、四、五、六",
            "資源回收": "一、二、四、五、六"
        },
        {
            "清運序": "12",
            "清運點名稱描述": "臺中市大雅區神林南路311號",
            "清運時間": "08:13",
            "一般垃圾": "一、二、四、五、六",
            "廚餘回收": "一、二、四、五、六",
            "資源回收": "一、二、四、五、六"
        },
        {
            "清運序": "13",
            "清運點名稱描述": "臺中市大雅區神林南路199號",
            "清運時間": "08:18",
            "一般垃圾": "一、二、四、五、六",
            "廚餘回收": "一、二、四、五、六",
            "資源回收": "一、二、四、五、六"
        },
        {
            "清運序": "14",
            "清運點名稱描述": "臺中市大雅區神林南路256號",
            "清運時間": "08:22",
            "一般垃圾": "一、二、四、五、六",
            "廚餘回收": "一、二、四、五、六",
            "資源回收": "一、二、四、五、六"
        },
        {
            "清運序": "15",
            "清運點名稱描述": "臺中市大雅區神林南路272巷41號",
            "清運時間": "08:25",
            "一般垃圾": "一、二、四、五、六",
            "廚餘回收": "一、二、四、五、六",
            "資源回收": "一、二、四、五、六"
        },
        {
            "清運序": "16",
            "清運點名稱描述": "臺中市大雅區神林南路312巷6號",
            "清運時間": "08:28",
            "一般垃圾": "一、二、四、五、六",
            "廚餘回收": "一、二、四、五、六",
            "資源回收": "一、二、四、五、六"
        },
        {
            "清運序": "17",
            "清運點名稱描述": "臺中市大雅區雅潭路四段506巷9號",
            "清運時間": "08:35",
            "一般垃圾": "一、二、四、五、六",
            "廚餘回收": "一、二、四、五、六",
            "資源回收": "一、二、四、五、六"
        },
        {
            "清運序": "18",
            "清運點名稱描述": "臺中市大雅區雅潭路四段542巷9號",
            "清運時間": "08:37",
            "一般垃圾": "一、二、四、五、六",
            "廚餘回收": "一、二、四、五、六",
            "資源回收": "一、二、四、五、六"
        },
        {
            "清運序": "19",
            "清運點名稱描述": "臺中市大雅區雅潭路四段600巷37弄6號",
            "清運時間": "08:42",
            "一般垃圾": "一、二、四、五、六",
            "廚餘回收": "一、二、四、五、六",
            "資源回收": "一、二、四、五、六"
        },
        {
            "清運序": "20",
            "清運點名稱描述": "臺中市大雅區雅潭路四段600巷80弄1號",
            "清運時間": "08:45",
            "一般垃圾": "一、二、四、五、六",
            "廚餘回收": "一、二、四、五、六",
            "資源回收": "一、二、四、五、六"
        },
        {
            "清運序": "21",
            "清運點名稱描述": "臺中市大雅區神林南路312巷1弄1號",
            "清運時間": "08:47",
            "一般垃圾": "一、二、四、五、六",
            "廚餘回收": "一、二、四、五、六",
            "資源回收": "一、二、四、五、六"
        },
        {
            "清運序": "22",
            "清運點名稱描述": "臺中市大雅區神林路一段36巷10號",
            "清運時間": "09:00",
            "一般垃圾": "一、二、四、五、六",
            "廚餘回收": "一、二、四、五、六",
            "資源回收": "一、二、四、五、六"
        },
        {
            "清運序": "23",
            "清運點名稱描述": "臺中市大雅區神林路一段49巷37號之1",
            "清運時間": "09:05",
            "一般垃圾": "一、二、四、五、六",
            "廚餘回收": "一、二、四、五、六",
            "資源回收": "一、二、四、五、六"
        },
        {
            "清運序": "24",
            "清運點名稱描述": "臺中市大雅區神林路一段49巷11號",
            "清運時間": "09:10",
            "一般垃圾": "一、二、四、五、六",
            "廚餘回收": "一、二、四、五、六",
            "資源回收": "一、二、四、五、六"
        },
        {
            "清運序": "25",
            "清運點名稱描述": "臺中市大雅區神林路一段49巷68號",
            "清運時間": "09:13",
            "一般垃圾": "一、二、四、五、六",
            "廚餘回收": "一、二、四、五、六",
            "資源回收": "一、二、四、五、六"
        },
        {
            "清運序": "26",
            "清運點名稱描述": "臺中市大雅區大林路140巷66弄5~7號",
            "清運時間": "09:14",
            "一般垃圾": "一、二、四、五、六",
            "廚餘回收": "一、二、四、五、六",
            "資源回收": "一、二、四、五、六"
        },
        {
            "清運序": "27",
            "清運點名稱描述": "臺中市大雅區大林路140巷48之8號",
            "清運時間": "09:17",
            "一般垃圾": "一、二、四、五、六",
            "廚餘回收": "一、二、四、五、六",
            "資源回收": "一、二、四、五、六"
        },
        {
            "清運序": "28",
            "清運點名稱描述": "臺中市大雅區大林路140巷40號",
            "清運時間": "09:20",
            "一般垃圾": "一、二、四、五、六",
            "廚餘回收": "一、二、四、五、六",
            "資源回收": "一、二、四、五、六"
        },
        {
            "清運序": "29",
            "清運點名稱描述": "臺中市大雅區大林路140巷78號",
            "清運時間": "09:24",
            "一般垃圾": "一、二、四、五、六",
            "廚餘回收": "一、二、四、五、六",
            "資源回收": "一、二、四、五、六"
        },
        {
            "清運序": "30",
            "清運點名稱描述": "臺中市大雅區大林路140巷116號",
            "清運時間": "09:26",
            "一般垃圾": "一、二、四、五、六",
            "廚餘回收": "一、二、四、五、六",
            "資源回收": "一、二、四、五、六"
        },
        {
            "清運序": "31",
            "清運點名稱描述": "臺中市大雅區大林路140巷105之1號",
            "清運時間": "09:29",
            "一般垃圾": "一、二、四、五、六",
            "廚餘回收": "一、二、四、五、六",
            "資源回收": "一、二、四、五、六"
        },
        {
            "清運序": "32",
            "清運點名稱描述": "臺中市大雅區大林路66巷58弄1號",
            "清運時間": "09:31",
            "一般垃圾": "一、二、四、五、六",
            "廚餘回收": "一、二、四、五、六",
            "資源回收": "一、二、四、五、六"
        },
        {
            "清運序": "33",
            "清運點名稱描述": "臺中市大雅區大林路66巷8號",
            "清運時間": "09:33",
            "一般垃圾": "一、二、四、五、六",
            "廚餘回收": "一、二、四、五、六",
            "資源回收": "一、二、四、五、六"
        },
        {
            "清運序": "34",
            "清運點名稱描述": "臺中市大雅區大林路65巷11號",
            "清運時間": "09:35",
            "一般垃圾": "一、二、四、五、六",
            "廚餘回收": "一、二、四、五、六",
            "資源回收": "一、二、四、五、六"
        },
        {
            "清運序": "35",
            "清運點名稱描述": "臺中市大雅區大林路7巷26號",
            "清運時間": "09:38",
            "一般垃圾": "一、二、四、五、六",
            "廚餘回收": "一、二、四、五、六",
            "資源回收": "一、二、四、五、六"
        },
        {
            "清運序": "36",
            "清運點名稱描述": "臺中市大雅區大林路3之1號",
            "清運時間": "09:45",
            "一般垃圾": "一、二、四、五、六",
            "廚餘回收": "一、二、四、五、六",
            "資源回收": "一、二、四、五、六"
        },
        {
            "清運序": "37",
            "清運點名稱描述": "臺中市大雅區學府路157號",
            "清運時間": "11:00",
            "一般垃圾": "一、二、四、五、六",
            "廚餘回收": "一、二、四、五、六",
            "資源回收": "一、二、四、五、六"
        },
        {
            "清運序": "38",
            "清運點名稱描述": "臺中市大雅區學府路121號",
            "清運時間": "11:10",
            "一般垃圾": "一、二、四、五、六",
            "廚餘回收": "一、二、四、五、六",
            "資源回收": "一、二、四、五、六"
        },
        {
            "清運序": "39",
            "清運點名稱描述": "臺中市大雅區神林南路539巷16號",
            "清運時間": "11:15",
            "一般垃圾": "一、二、四、五、六",
            "廚餘回收": "一、二、四、五、六",
            "資源回收": "一、二、四、五、六"
        },
        {
            "清運序": "40",
            "清運點名稱描述": "臺中市大雅區雅環路一段170號",
            "清運時間": "11:20",
            "一般垃圾": "一、二、四、五、六",
            "廚餘回收": "一、二、四、五、六",
            "資源回收": "一、二、四、五、六"
        },
        {
            "清運序": "41",
            "清運點名稱描述": "臺中市大雅區雅潭路4段686號",
            "清運時間": "11:25",
            "一般垃圾": "一、二、四、五、六",
            "廚餘回收": "一、二、四、五、六",
            "資源回收": "一、二、四、五、六"
        },
        {
            "清運序": "42",
            "清運點名稱描述": "臺中市大雅區雅潭路四段800號(大雅圖書館前)",
            "清運時間": "11:30",
            "一般垃圾": "一、二、四、五、六",
            "廚餘回收": "一、二、四、五、六",
            "資源回收": "一、二、四、五、六"
        },
        {
            "清運序": "43",
            "清運點名稱描述": "臺中市大雅區雅潭路四段617號",
            "清運時間": "11:40",
            "一般垃圾": "一、二、四、五、六",
            "廚餘回收": "一、二、四、五、六",
            "資源回收": "一、二、四、五、六"
        },
        {
            "清運序": "44",
            "清運點名稱描述": "臺中市大雅區大林路121巷59號",
            "清運時間": "12:00",
            "一般垃圾": "一、二、四、五、六",
            "廚餘回收": "一、二、四、五、六",
            "資源回收": "一、二、四、五、六"
        },
        {
            "清運序": "45",
            "清運點名稱描述": "臺中市大雅區光復路19之5號",
            "清運時間": "12:10",
            "一般垃圾": "一、二、四、五、六",
            "廚餘回收": "一、二、四、五、六",
            "資源回收": "一、二、四、五、六"
        },
        {
            "清運序": "46",
            "清運點名稱描述": "臺中市大雅區清陽一路39巷2號",
            "清運時間": "12:13",
            "一般垃圾": "一、二、四、五、六",
            "廚餘回收": "一、二、四、五、六",
            "資源回收": "一、二、四、五、六"
        },
        {
            "清運序": "47",
            "清運點名稱描述": "臺中市大雅區光復路24之9號",
            "清運時間": "12:18",
            "一般垃圾": "一、二、四、五、六",
            "廚餘回收": "一、二、四、五、六",
            "資源回收": "一、二、四、五、六"
        },
        {
            "清運序": "48",
            "清運點名稱描述": "臺中市大雅區清陽二路188號",
            "清運時間": "12:23",
            "一般垃圾": "一、二、四、五、六",
            "廚餘回收": "一、二、四、五、六",
            "資源回收": "一、二、四、五、六"
        },
        {
            "清運序": "49",
            "清運點名稱描述": "臺中市大雅區和平路2之1號",
            "清運時間": "12:40",
            "一般垃圾": "一、二、四、五、六",
            "廚餘回收": "一、二、四、五、六",
            "資源回收": "一、二、四、五、六"
        },
        {
            "清運序": "50",
            "清運點名稱描述": "臺中市大雅區和平路200之10號",
            "清運時間": "12:55",
            "一般垃圾": "一、二、四、五、六",
            "廚餘回收": "一、二、四、五、六",
            "資源回收": "一、二、四、五、六"
        },
        {
            "清運序": "51",
            "清運點名稱描述": "臺中市大雅區中清路四段861巷2號",
            "清運時間": "13:02",
            "一般垃圾": "一、二、四、五、六",
            "廚餘回收": "一、二、四、五、六",
            "資源回收": "一、二、四、五、六"
        },
        {
            "清運序": "52",
            "清運點名稱描述": "臺中市大雅區中清路四段861巷35號",
            "清運時間": "13:07",
            "一般垃圾": "一、二、四、五、六",
            "廚餘回收": "一、二、四、五、六",
            "資源回收": "一、二、四、五、六"
        },
        {
            "清運序": "53",
            "清運點名稱描述": "臺中市大雅區中清路四段903巷18號",
            "清運時間": "13:11",
            "一般垃圾": "一、二、四、五、六",
            "廚餘回收": "一、二、四、五、六",
            "資源回收": "一、二、四、五、六"
        }
    ]
}