{
    "meta": {
        "縣市別": "臺中市",
        "鄉鎮市區": "清水區",
        "清運路線序號": "B43610001",
        "清運路線名稱": "N-01",
        "清運方式": "定點清運",
        "清運車輛車號": "103S6(備用車號:777S7)",
        "清運路線距離(公里)": "61.00",
        "每日清運垃圾量(公噸\/日)": "2.24",
        "清運頻率(週)": "5",
        "清運頻率(日)": "1"
    },
    "points": [
        {
            "清運序": "1",
            "清運點名稱描述": "臨江里鎮明路10之30號前",
            "清運時間": "21:00",
            "一般垃圾": "一、二、四、五、六",
            "廚餘回收": "一、二、四、五、六",
            "資源回收": "一、二、四、五、六"
        },
        {
            "清運序": "2",
            "清運點名稱描述": "臨江里高美路420號(四塊厝朝天宮馬祖廟前)",
            "清運時間": "21:00",
            "一般垃圾": "一、二、四、五、六",
            "廚餘回收": "一、二、四、五、六",
            "資源回收": "一、二、四、五、六"
        },
        {
            "清運序": "3",
            "清運點名稱描述": "高南里高美路469之7號前",
            "清運時間": "21:00",
            "一般垃圾": "一、二、四、五、六",
            "廚餘回收": "一、二、四、五、六",
            "資源回收": "一、二、四、五、六"
        },
        {
            "清運序": "4",
            "清運點名稱描述": "高南里高美路497號旁(舊庄車牌下)",
            "清運時間": "21:00",
            "一般垃圾": "一、二、四、五、六",
            "廚餘回收": "一、二、四、五、六",
            "資源回收": "一、二、四、五、六"
        },
        {
            "清運序": "5",
            "清運點名稱描述": "高美里護岸路43-1號對面",
            "清運時間": "21:00",
            "一般垃圾": "一、二、四、五、六",
            "廚餘回收": "一、二、四、五、六",
            "資源回收": "一、二、四、五、六"
        },
        {
            "清運序": "6",
            "清運點名稱描述": "高北里海口北路88號前廣場",
            "清運時間": "21:00",
            "一般垃圾": "一、二、四、五、六",
            "廚餘回收": "一、二、四、五、六",
            "資源回收": "一、二、四、五、六"
        },
        {
            "清運序": "7",
            "清運點名稱描述": "高西里高美路721巷4號(舊西安壇文興宮)",
            "清運時間": "21:00",
            "一般垃圾": "一、二、四、五、六",
            "廚餘回收": "一、二、四、五、六",
            "資源回收": "一、二、四、五、六"
        },
        {
            "清運序": "8",
            "清運點名稱描述": "高西里高美路720之38號(進興宮前)",
            "清運時間": "21:00",
            "一般垃圾": "一、二、四、五、六",
            "廚餘回收": "一、二、四、五、六",
            "資源回收": "一、二、四、五、六"
        },
        {
            "清運序": "9",
            "清運點名稱描述": "高東里三美路232號對面(土地公廟前)",
            "清運時間": "21:00",
            "一般垃圾": "一、二、四、五、六",
            "廚餘回收": "一、二、四、五、六",
            "資源回收": "一、二、四、五、六"
        },
        {
            "清運序": "10",
            "清運點名稱描述": "國姓里三美路136號前",
            "清運時間": "21:00",
            "一般垃圾": "一、二、四、五、六",
            "廚餘回收": "一、二、四、五、六",
            "資源回收": "一、二、四、五、六"
        },
        {
            "清運序": "11",
            "清運點名稱描述": "國姓里三美路129之8號前",
            "清運時間": "21:00",
            "一般垃圾": "一、二、四、五、六",
            "廚餘回收": "一、二、四、五、六",
            "資源回收": "一、二、四、五、六"
        }
    ]
}